atsdpc/Evaluation.py
atsdpc/__init__.py
atsdpc/clustering_utils.py
atsdpc/main.py
atsdpc/metrics.py
atsdpc-1.1.5.dist-info/METADATA
atsdpc-1.1.5.dist-info/WHEEL
atsdpc-1.1.5.dist-info/top_level.txt
atsdpc-1.1.5.dist-info/RECORD
