Metadata-Version: 2.1
Name: atsdpc
Version: 1.1.5
Summary: ATSDPC Clustering Package
Home-page: https://github.com/yourusername/atsdpc
Author: Shengqiang Han
Author-email: 2023028101@stu.sdnu.edu.cn
Classifier: Programming Language :: Python :: 3
Classifier: License :: OSI Approved :: MIT License
Classifier: Operating System :: OS Independent
Requires-Python: >=3.6
Requires-Dist: pandas
Requires-Dist: numpy
Requires-Dist: matplotlib
Requires-Dist: scikit-learn
Requires-Dist: scipy
